{"name":"Segundo escenario - Manejo de selenium","id":"prueba-técnica-–-automatización;segundo-escenario---manejo-de-selenium","testSteps":[{"number":1,"description":"Dada la siguiente url \"https://somosmakers.co/\"","duration":6168,"startTime":"2022-04-12T00:17:25.348240900-05:00[America/Bogota]","result":"SUCCESS","precondition":false,"level":0,"children":[{"number":2,"description":"Lanzar navegador: https://somosmakers.co/","duration":5399,"startTime":"2022-04-12T00:17:26.103980600-05:00[America/Bogota]","result":"SUCCESS","precondition":false,"level":1}]},{"number":3,"description":"Cuando hacemos clic en el enlace de \"CONTACTO\"","duration":1540,"startTime":"2022-04-12T00:17:31.523434-05:00[America/Bogota]","result":"SUCCESS","precondition":false,"level":0,"children":[{"number":4,"description":"Formulario contacto","duration":1534,"startTime":"2022-04-12T00:17:31.528421600-05:00[America/Bogota]","result":"SUCCESS","precondition":false,"level":1}]},{"number":5,"description":"Entonces capturar el numero de celular de servicio al cliente","duration":1,"startTime":"2022-04-12T00:17:33.066369200-05:00[America/Bogota]","result":"SUCCESS","precondition":false,"level":0},{"number":6,"description":"Y llenar el formulario \"dejanos un mensaje\" y en el campo mensaje adjuntar el numero de celular capturado","duration":1741,"startTime":"2022-04-12T00:17:33.069360900-05:00[America/Bogota]","result":"SUCCESS","precondition":false,"level":0,"children":[{"number":7,"description":"Diligenciar datos","duration":1734,"startTime":"2022-04-12T00:17:33.074347800-05:00[America/Bogota]","result":"SUCCESS","precondition":false,"level":1}]},{"number":8,"description":"Y antes de hacer clic en el boton \"enviar mensaje\" tomar un pantallazo con la informacion diligenciada","duration":12544,"startTime":"2022-04-12T00:17:34.811691100-05:00[America/Bogota]","result":"SUCCESS","precondition":false,"level":0,"children":[{"number":9,"description":"Mensaje","duration":12407,"startTime":"2022-04-12T00:17:34.823658500-05:00[America/Bogota]","result":"SUCCESS","precondition":false,"level":1}]}],"userStory":{"id":"prueba-técnica-–-automatización","storyName":"Prueba técnica – Automatización","path":"src/test/resources/features/ManejoSelenium.feature","type":"feature"},"featureTag":{"name":"Features/Prueba técnica – Automatización","type":"feature","displayName":"Features/Prueba técnica – Automatización"},"title":"Segundo escenario - Manejo de selenium","tags":[{"name":"Prueba técnica – Automatización","type":"feature","displayName":"Prueba técnica – Automatización"},{"name":"ManejoSelenium","type":"tag","displayName":"ManejoSelenium"}],"startTime":"2022-04-12T00:17:25.205113600-05:00[America/Bogota]","duration":22159,"projectKey":"","isManualTestingUpToDate":false,"manual":false,"testSource":"Cucumber","result":"SUCCESS"}